CHANGES.txt
MANIFEST.in
README.md
setup.py
test.py
py_goicp.egg-info/PKG-INFO
py_goicp.egg-info/SOURCES.txt
py_goicp.egg-info/dependency_links.txt
py_goicp.egg-info/not-zip-safe
py_goicp.egg-info/requires.txt
py_goicp.egg-info/top_level.txt
src/goicpcc.pxd
src/jly_3ddt.hpp
src/jly_goicp.hpp
src/jly_icp3d.hpp
src/jly_sorting.hpp
src/matrix.hpp
src/nanoflann.hpp