Metadata-Version: 2.1
Name: py-goicp
Version: 0.0.4
Summary: GO-ICP compiled using Cython to use in python
Home-page: https://github.com/aalavandhaann/go-icp_cython
Author: #0K Srinivasan Ramachandran
Author-email: ashok.srinivasan2002@gmail.com
Maintainer: #0K Srinivasan Ramachandran
Maintainer-email: ashok.srinivasan2002@gmail.com
License: LICENSE.txt
Keywords: icp go-icp registration alignment rigid-align rigid-alignment
Platform: any
Requires-Python: >=2
